<record><leader>00000cas a22000007a 4500</leader><controlfield tag="001">13775559</controlfield><controlfield tag="008">860625d19281935nvuwr ne      0    0eng d</controlfield><datafield ind1=" " ind2=" " tag="010"><subfield code="a">sn 86076273 </subfield></datafield><datafield ind1=" " ind2=" " tag="040"><subfield code="a">NNX</subfield><subfield code="b">eng</subfield><subfield code="c">NNX</subfield><subfield code="d">CNK</subfield><subfield code="d">OCLCQ</subfield></datafield><datafield ind1=" " ind2=" " tag="042"><subfield code="a">msc</subfield></datafield><datafield ind1="0" ind2="0" tag="245"><subfield code="a">Hawthorne news.</subfield></datafield><datafield ind1=" " ind2=" " tag="260"><subfield code="a">Hawthorne, Nev. :</subfield><subfield code="b">Hawthorne News Print. Co.</subfield></datafield><datafield ind1=" " ind2=" " tag="300"><subfield code="a">v. :</subfield><subfield code="b">ill.</subfield></datafield><datafield ind1=" " ind2=" " tag="310"><subfield code="a">Weekly</subfield></datafield><datafield ind1="1" ind2=" " tag="362"><subfield code="a">Began with Aug. 29, 1928 issue; ceased with June 15, 1935 issue.</subfield><subfield code="z">Cf. Lingenfelter, R. Newspapers of Nev., 1854-1979.</subfield></datafield><datafield ind1=" " ind2=" " tag="588"><subfield code="a">Description based on: Vol. 3, no. 21 (Jan. 14, 1931).</subfield></datafield><datafield ind1=" " ind2=" " tag="752"><subfield code="a">United States</subfield><subfield code="b">Nevada</subfield><subfield code="c">Mineral</subfield><subfield code="d">Hawthorne.</subfield></datafield><datafield ind1="0" ind2="7" tag="785"><subfield code="t">Mineral County independent</subfield><subfield code="w">(DLC)sn 86076225</subfield></datafield><datafield ind1="0" ind2="7" tag="785"><subfield code="t">Mineral County independent and Hawthorne news</subfield><subfield code="w">(DLC)sn 86076244</subfield><subfield code="w">(OCoLC)13775514</subfield></datafield></record>