<record><leader>00000cas a22000007a 4500</leader><controlfield tag="001">18180918</controlfield><controlfield tag="008">880707d18811uuutxuuu ne      0    0eng d</controlfield><datafield ind1=" " ind2=" " tag="010"><subfield code="a">sn 88083876 </subfield></datafield><datafield ind1=" " ind2=" " tag="040"><subfield code="a">PPM</subfield><subfield code="b">eng</subfield><subfield code="c">PPM</subfield><subfield code="d">OCLCQ</subfield></datafield><datafield ind1=" " ind2=" " tag="042"><subfield code="a">msc</subfield></datafield><datafield ind1="0" ind2=" " tag="130"><subfield code="a">Texas tribune (Paris, Tex.)</subfield></datafield><datafield ind1="1" ind2="4" tag="245"><subfield code="a">The Texas tribune.</subfield></datafield><datafield ind1=" " ind2=" " tag="260"><subfield code="a">Paris, Tex. :</subfield><subfield code="b">J.E. Ellis &amp; A.H. Boyd,</subfield><subfield code="c">1881-</subfield></datafield><datafield ind1="0" ind2=" " tag="362"><subfield code="a">Vol. 1, Ke. 1 (Dec. 15, 1881)-</subfield></datafield><datafield ind1=" " ind2=" " tag="752"><subfield code="a">United States</subfield><subfield code="b">Texas</subfield><subfield code="c">Lamar</subfield><subfield code="d">Paris.</subfield></datafield></record>