<record><leader>00000cas a22000007a 4500</leader><controlfield tag="001">16658360</controlfield><controlfield tag="008">870909d19151922iauwr ne      0    0eng d</controlfield><datafield ind1=" " ind2=" " tag="010"><subfield code="a">sn 87057829 </subfield></datafield><datafield ind1=" " ind2=" " tag="040"><subfield code="a">INP</subfield><subfield code="b">eng</subfield><subfield code="c">INP</subfield><subfield code="d">OCLCQ</subfield></datafield><datafield ind1=" " ind2=" " tag="042"><subfield code="a">msc</subfield></datafield><datafield ind1="0" ind2="4" tag="245"><subfield code="a">The Grand Junction globe and the Paton portrait.</subfield></datafield><datafield ind1="1" ind2="3" tag="246"><subfield code="a">Grand Junction globe and Paton portrait</subfield></datafield><datafield ind1=" " ind2=" " tag="260"><subfield code="a">Grand Junction, Iowa :</subfield><subfield code="b">F.L. Mott,</subfield><subfield code="c">1915-1922.</subfield></datafield><datafield ind1=" " ind2=" " tag="300"><subfield code="a">8 v.</subfield></datafield><datafield ind1=" " ind2=" " tag="310"><subfield code="a">Weekly</subfield></datafield><datafield ind1="0" ind2=" " tag="362"><subfield code="a">Vol. 44, no. 38 (Sept. 30, 1915)-v. 51, no. 35 (Aug. 31, 1922).</subfield></datafield><datafield ind1=" " ind2=" " tag="500"><subfield code="a">Includes section called: The Paton portrait and Grand Junction globe, June 27, 1918-Aug. 31, 1922.</subfield></datafield><datafield ind1=" " ind2=" " tag="752"><subfield code="a">United States</subfield><subfield code="b">Iowa</subfield><subfield code="c">Greene</subfield><subfield code="d">Grand Junction.</subfield></datafield><datafield ind1=" " ind2=" " tag="752"><subfield code="a">United States</subfield><subfield code="b">Iowa</subfield><subfield code="c">Greene</subfield><subfield code="d">Paton.</subfield></datafield><datafield ind1="0" ind2="0" tag="780"><subfield code="t">Grand Junction globe</subfield><subfield code="w">(DLC)sn 87057827</subfield></datafield><datafield ind1="0" ind2="7" tag="785"><subfield code="t">Rippey booster</subfield></datafield><datafield ind1="0" ind2="7" tag="785"><subfield code="t">Grand Junction globe and the Paton portrait and the Rippey news</subfield><subfield code="w">(DLC)sn 87057830</subfield></datafield><datafield ind1="1" ind2=" " tag="787"><subfield code="t">Paton portrait and Grand Junction globe</subfield></datafield></record>