<record><leader>00000cas a2200000I  4500</leader><controlfield tag="001">8500261</controlfield><controlfield tag="008">820608d19311934vaumr n       0   a0eng d</controlfield><controlfield tag="009">424</controlfield><datafield ind1=" " ind2=" " tag="010"><subfield code="a">sn 94060125 </subfield></datafield><datafield ind1=" " ind2=" " tag="040"><subfield code="a">VIC</subfield><subfield code="c">VIC</subfield><subfield code="d">NVK</subfield><subfield code="d">OCL</subfield><subfield code="d">NVK</subfield><subfield code="d">OCLCQ</subfield></datafield><datafield ind1=" " ind2=" " tag="043"><subfield code="a">n-us-va</subfield></datafield><datafield ind1=" " ind2=" " tag="090"><subfield code="a">TH6101</subfield><subfield code="b">.H4</subfield></datafield><datafield ind1="0" ind2="0" tag="245"><subfield code="a">Heating and plumbing news.</subfield></datafield><datafield ind1=" " ind2=" " tag="260"><subfield code="a">[Richmond, Va.,</subfield><subfield code="b">Master Plumbers and Heating Association of Richmond, Va.],</subfield></datafield><datafield ind1=" " ind2=" " tag="300"><subfield code="a">v.</subfield></datafield><datafield ind1=" " ind2=" " tag="310"><subfield code="a">Monthly</subfield></datafield><datafield ind1="0" ind2=" " tag="362"><subfield code="a">Vol. 1, no. 1 (Feb. 1931)-</subfield></datafield><datafield ind1="1" ind2=" " tag="362"><subfield code="a">Ceased in 1934.</subfield></datafield><datafield ind1=" " ind2=" " tag="500"><subfield code="a">Edited by R.H. Griffin.</subfield></datafield><datafield ind1=" " ind2=" " tag="500"><subfield code="a">"A progressive monthly newspaper devoted to the advancement of heating and plumbing in Virginia."</subfield></datafield><datafield ind1=" " ind2=" " tag="515"><subfield code="a">Nos. 27-31, 36 are combined issues.</subfield></datafield><datafield ind1=" " ind2="0" tag="650"><subfield code="a">Plumbing</subfield><subfield code="v">Newspapers.</subfield></datafield><datafield ind1=" " ind2="0" tag="650"><subfield code="a">Heating</subfield><subfield code="v">Newspapers.</subfield></datafield><datafield ind1=" " ind2="0" tag="651"><subfield code="a">Richmond (Va.)</subfield><subfield code="v">Newspapers.</subfield></datafield><datafield ind1="1" ind2=" " tag="700"><subfield code="a">Griffin, Rosser H.</subfield></datafield><datafield ind1=" " ind2=" " tag="752"><subfield code="a">United States</subfield><subfield code="b">Virginia</subfield><subfield code="d">Richmond.</subfield></datafield></record>