<record><leader>00000cas a22000007a 4500</leader><controlfield tag="001">13944761</controlfield><controlfield tag="008">860725d18391839vauir ne      0    0eng  </controlfield><controlfield tag="009">466</controlfield><datafield ind1=" " ind2=" " tag="010"><subfield code="a">sn 86071750 </subfield></datafield><datafield ind1=" " ind2=" " tag="040"><subfield code="a">DLC</subfield><subfield code="b">eng</subfield><subfield code="c">DLC</subfield></datafield><datafield ind1="1" ind2=" " tag="029"><subfield code="a">AU@</subfield><subfield code="b">000025790926</subfield></datafield><datafield ind1=" " ind2=" " tag="042"><subfield code="a">msc</subfield></datafield><datafield ind1="0" ind2="0" tag="050"><subfield code="a">Newspaper 10082</subfield></datafield><datafield ind1="0" ind2=" " tag="130"><subfield code="a">Commercial chronicle (Portsmouth, Va.)</subfield></datafield><datafield ind1="0" ind2="0" tag="245"><subfield code="a">Commercial chronicle.</subfield></datafield><datafield ind1=" " ind2=" " tag="260"><subfield code="a">Portsmouth, Va. :</subfield><subfield code="b">Theophilus Fisk,</subfield><subfield code="c">1839.</subfield></datafield><datafield ind1=" " ind2=" " tag="300"><subfield code="a">1 v. :</subfield><subfield code="b">ill. (chiefly advertisements) ;</subfield><subfield code="c">55 cm.</subfield></datafield><datafield ind1=" " ind2=" " tag="310"><subfield code="a">Triweekly</subfield></datafield><datafield ind1="0" ind2=" " tag="362"><subfield code="a">Vol. 1, no. 1 (Apr. 18, 1839)-v. 1, no. 65 (Sept. 18, 1839).</subfield></datafield><datafield ind1=" " ind2=" " tag="752"><subfield code="a">United States</subfield><subfield code="b">Virginia</subfield><subfield code="d">Portsmouth.</subfield></datafield><datafield ind1="0" ind2="0" tag="785"><subfield code="t">Commercial chronicle, and the Portsmouth and Norfolk tri-weekly Old Dominion</subfield><subfield code="w">(DLC)sn 86071751</subfield></datafield></record>