<record><leader>00000cas a22000007a 4500</leader><controlfield tag="001">13291694</controlfield><controlfield tag="008">860313d19001916wvuwr ne      0    0eng d</controlfield><controlfield tag="009">6116</controlfield><datafield ind1=" " ind2=" " tag="010"><subfield code="a">sn 86092382 </subfield></datafield><datafield ind1=" " ind2=" " tag="040"><subfield code="a">WVC</subfield><subfield code="b">eng</subfield><subfield code="c">WVC</subfield><subfield code="d">DLC</subfield><subfield code="d">OCL</subfield></datafield><datafield ind1=" " ind2=" " tag="042"><subfield code="a">msc</subfield></datafield><datafield ind1="0" ind2="4" tag="245"><subfield code="a">The Buckhannon delta and knight errant.</subfield></datafield><datafield ind1=" " ind2=" " tag="260"><subfield code="a">Buckhannon, W. Va. :</subfield><subfield code="b">Knight Errant Co.,</subfield><subfield code="c">1900-</subfield></datafield><datafield ind1=" " ind2=" " tag="300"><subfield code="a">v.</subfield></datafield><datafield ind1=" " ind2=" " tag="310"><subfield code="a">Weekly,</subfield><subfield code="b">1911-1916</subfield></datafield><datafield ind1=" " ind2=" " tag="321"><subfield code="a">Weekly,</subfield><subfield code="b">1900-1910</subfield></datafield><datafield ind1=" " ind2=" " tag="321"><subfield code="a">Semiweekly,</subfield><subfield code="b">1910-1911</subfield></datafield><datafield ind1="0" ind2=" " tag="362"><subfield code="a">Vol. 31, no. 3 (Jan. 25, 1900)-</subfield></datafield><datafield ind1="1" ind2=" " tag="362"><subfield code="a">Ceased in 1916?</subfield></datafield><datafield ind1=" " ind2=" " tag="515"><subfield code="a">Continued the numbering of: Buckhannon delta.</subfield></datafield><datafield ind1=" " ind2=" " tag="752"><subfield code="a">United States</subfield><subfield code="b">West Virginia</subfield><subfield code="c">Upshur</subfield><subfield code="d">Buckhannon.</subfield></datafield><datafield ind1="0" ind2="4" tag="780"><subfield code="t">Knight-errant (Buckhannon, W.Va.)</subfield><subfield code="w">(DLC)sn 86092381</subfield></datafield><datafield ind1="0" ind2="4" tag="780"><subfield code="t">Buckhannon delta (Buckhannon, W.Va. : 1871)</subfield><subfield code="w">(DLC)sn 84026783</subfield></datafield><datafield ind1="0" ind2="0" tag="785"><subfield code="t">Buckhannon delta (Buckhannon, W.Va. : 1916)</subfield><subfield code="w">(DLC)sn 86092383</subfield></datafield></record>