<record><leader>00000cas a22000007a 4500</leader><controlfield tag="001">56203379</controlfield><controlfield tag="008">040816c20029999gaucr ne      0   a0eng  </controlfield><datafield ind1=" " ind2=" " tag="010"><subfield code="a">  2004213143</subfield></datafield><datafield ind1=" " ind2=" " tag="040"><subfield code="a">NSD</subfield><subfield code="b">eng</subfield><subfield code="c">NSD</subfield><subfield code="d">OCLCQ</subfield><subfield code="d">GUA</subfield><subfield code="d">DLC</subfield><subfield code="d">OCLCF</subfield><subfield code="d">OCLCO</subfield><subfield code="d">GUA</subfield></datafield><datafield ind1=" " ind2=" " tag="012"><subfield code="m">y</subfield></datafield><datafield ind1="0" ind2=" " tag="022"><subfield code="a">1551-8353</subfield><subfield code="y">1055-6509</subfield><subfield code="2">1</subfield></datafield><datafield ind1=" " ind2=" " tag="032"><subfield code="a">086604</subfield><subfield code="b">USPS</subfield></datafield><datafield ind1=" " ind2=" " tag="037"><subfield code="b">Community Newspapers Inc., P.O. Box 470, 707 Osborne St., St. Mary's Georgia 31558</subfield></datafield><datafield ind1=" " ind2=" " tag="042"><subfield code="a">pcc</subfield><subfield code="a">nsdp</subfield></datafield><datafield ind1=" " ind2=" " tag="043"><subfield code="a">n-us-ga</subfield></datafield><datafield ind1=" " ind2="0" tag="222"><subfield code="a">Tribune &amp; Georgian</subfield></datafield><datafield ind1="0" ind2="0" tag="245"><subfield code="a">Tribune &amp; Georgian.</subfield></datafield><datafield ind1="1" ind2=" " tag="246"><subfield code="a">Tribune and Georgian</subfield></datafield><datafield ind1=" " ind2=" " tag="260"><subfield code="a">Athens, Ga. :</subfield><subfield code="b">Community Newspapers Inc.</subfield></datafield><datafield ind1=" " ind2=" " tag="300"><subfield code="a">v.</subfield></datafield><datafield ind1=" " ind2=" " tag="310"><subfield code="a">Semiweekly</subfield></datafield><datafield ind1="1" ind2=" " tag="362"><subfield code="a">Began with Apr. 24, 2002 issue.</subfield></datafield><datafield ind1=" " ind2=" " tag="515"><subfield code="a">Apr. 24, 2002 issue called April 24, 2001 on masthead in error.</subfield></datafield><datafield ind1=" " ind2=" " tag="525"><subfield code="a">Has various named supplements: Relay for life, May 10, 2002; Paragon, May 29, 2002; Red, white &amp; blue, June 20, 2002; Coastal Georgia Community College. Schedule of classes, July 24, 2002; School scene, August 2, 2002; Wildcats, August 30, 2002.</subfield></datafield><datafield ind1=" " ind2=" " tag="588"><subfield code="a">Description based on: Apr. 26, 2012.</subfield></datafield><datafield ind1=" " ind2=" " tag="588"><subfield code="a">Latest issue consulted: Vol. 102, no. 3 (Jan. 12, 2005).</subfield></datafield><datafield ind1=" " ind2="0" tag="651"><subfield code="a">Camden County (Ga.)</subfield><subfield code="v">Newspapers.</subfield></datafield><datafield ind1=" " ind2="7" tag="651"><subfield code="a">Georgia</subfield><subfield code="z">Camden County.</subfield><subfield code="2">fast</subfield><subfield code="0">(OCoLC)fst01214074</subfield></datafield><datafield ind1=" " ind2="7" tag="655"><subfield code="a">Newspapers.</subfield><subfield code="2">fast</subfield><subfield code="0">(OCoLC)fst01423814</subfield></datafield><datafield ind1="0" ind2=" " tag="730"><subfield code="a">Relay for life.</subfield></datafield><datafield ind1="0" ind2=" " tag="730"><subfield code="a">Paragon.</subfield></datafield><datafield ind1="0" ind2=" " tag="730"><subfield code="a">Red, white &amp; blue.</subfield></datafield><datafield ind1="0" ind2=" " tag="730"><subfield code="a">Schedule of classes.</subfield></datafield><datafield ind1="0" ind2=" " tag="730"><subfield code="a">School scene.</subfield></datafield><datafield ind1="0" ind2=" " tag="730"><subfield code="a">Wildcats.</subfield></datafield><datafield ind1=" " ind2=" " tag="752"><subfield code="a">United States</subfield><subfield code="b">Georgia</subfield><subfield code="c">Athens-Clarke</subfield><subfield code="d">Athens.</subfield></datafield><datafield ind1="0" ind2="0" tag="780"><subfield code="t">Camden County tribune &amp; the southeast Georgian</subfield><subfield code="x">1551-8345</subfield><subfield code="w">(DLC)  2002233219</subfield><subfield code="w">(OCoLC)51512994</subfield></datafield></record>