<record><leader>00000cas a22000007a 4500</leader><controlfield tag="001">17974710</controlfield><controlfield tag="008">880519d18961uuunyucr ne      0    0eng d</controlfield><datafield ind1=" " ind2=" " tag="010"><subfield code="a">sn 88075705 </subfield></datafield><datafield ind1=" " ind2=" " tag="040"><subfield code="a">NYG</subfield><subfield code="b">eng</subfield><subfield code="c">NYG</subfield><subfield code="d">NYS</subfield><subfield code="d">OCLCQ</subfield></datafield><datafield ind1="0" ind2="0" tag="245"><subfield code="a">Utica semi-weekly herald and gazette and courier.</subfield></datafield><datafield ind1="1" ind2="7" tag="246"><subfield code="a">Utica semi-weekly herald</subfield></datafield><datafield ind1=" " ind2=" " tag="260"><subfield code="a">Utica, N.Y. :</subfield><subfield code="b">[Utica Herald Pub. Co.],</subfield><subfield code="c">1896-</subfield></datafield><datafield ind1=" " ind2=" " tag="300"><subfield code="a">v.</subfield></datafield><datafield ind1=" " ind2=" " tag="310"><subfield code="a">Semiweekly</subfield></datafield><datafield ind1="0" ind2=" " tag="362"><subfield code="a">Vol. 48, no. 33 (June 2, 1896)-</subfield></datafield><datafield ind1=" " ind2=" " tag="500"><subfield code="a">Published on Tuesday and Friday.</subfield></datafield><datafield ind1=" " ind2="4" tag="651"><subfield code="a">Utica (N.Y.)</subfield><subfield code="v">Newspapers.</subfield></datafield><datafield ind1=" " ind2=" " tag="752"><subfield code="a">United States</subfield><subfield code="b">New York</subfield><subfield code="c">Oneida</subfield><subfield code="d">Utica.</subfield></datafield><datafield ind1="0" ind2=" " tag="775"><subfield code="t">Utica morning herald and daily gazette</subfield><subfield code="w">(DLC)sn 83031871</subfield></datafield><datafield ind1="0" ind2="0" tag="780"><subfield code="t">Utica weekly herald and gazette and courier</subfield><subfield code="w">(DLC)sn 86053206</subfield></datafield></record>