<record><leader>00000cas a22000007a 4500</leader><controlfield tag="001">16940428</controlfield><controlfield tag="008">871105d190519uutxuwr ne      0    0eng d</controlfield><datafield ind1=" " ind2=" " tag="010"><subfield code="a">sn 87091111 </subfield></datafield><datafield ind1=" " ind2=" " tag="040"><subfield code="a">PPM</subfield><subfield code="b">eng</subfield><subfield code="c">PPM</subfield><subfield code="d">OCLCQ</subfield></datafield><datafield ind1=" " ind2=" " tag="042"><subfield code="a">msc</subfield></datafield><datafield ind1="0" ind2="4" tag="245"><subfield code="a">The Stamford tribune.</subfield></datafield><datafield ind1=" " ind2=" " tag="260"><subfield code="a">Stamford, Tex. :</subfield><subfield code="b">James A. Greer</subfield></datafield><datafield ind1=" " ind2=" " tag="310"><subfield code="a">Weekly</subfield></datafield><datafield ind1="1" ind2=" " tag="362"><subfield code="a">Began in 1905?</subfield></datafield><datafield ind1=" " ind2=" " tag="588"><subfield code="a">Description based on: Vol. 2, no. 2 (Oct. 19, 1906).</subfield></datafield><datafield ind1=" " ind2=" " tag="752"><subfield code="a">United States</subfield><subfield code="b">Texas</subfield><subfield code="c">Jones</subfield><subfield code="d">Stamford.</subfield></datafield><datafield ind1="0" ind2="7" tag="785"><subfield code="t">Stamford news (Stamford, Tex.)</subfield><subfield code="w">(DLC)sn 86090269</subfield></datafield><datafield ind1="0" ind2="7" tag="785"><subfield code="t">Stamford news-tribune</subfield><subfield code="w">(DLC)sn 86089300</subfield></datafield></record>